kode_kronical/__init__.py
kode_kronical/config.py
kode_kronical/core.py
kode_kronical/daemon.py
kode_kronical/daemon_client.py
kode_kronical/default.yaml
kode_kronical/exception_handler.py
kode_kronical/failure_capture.py
kode_kronical/hostname_utils.py
kode_kronical/metrics_compression.py
kode_kronical/optimized_system_storage.py
kode_kronical/service_installer.py
kode_kronical/system_dynamodb.py
kode_kronical/system_monitor.py
kode_kronical/systems_registry.py
kode_kronical-0.7.1.dist-info/licenses/LICENSE
kode_kronical-0.7.1.dist-info/METADATA
kode_kronical-0.7.1.dist-info/WHEEL
kode_kronical-0.7.1.dist-info/entry_points.txt
kode_kronical-0.7.1.dist-info/top_level.txt
kode_kronical-0.7.1.dist-info/RECORD
