Metadata-Version: 2.4
Name: kode-kronical
Version: 0.7.1
Summary: A lightweight Python performance tracking library with automatic data collection and visualization
Author-email: Jeremy Gillespie <metalgear386@googlemail.com>
License: MIT
Project-URL: Homepage, https://github.com/jeremycharlesgillespie/kode-kronical
Project-URL: Documentation, https://kode-kronical.readthedocs.io/
Project-URL: Repository, https://github.com/jeremycharlesgillespie/kode-kronical
Project-URL: Bug Tracker, https://github.com/jeremycharlesgillespie/kode-kronical/issues
Keywords: performance,profiling,monitoring,timing,benchmarking
Classifier: Development Status :: 4 - Beta
Classifier: Intended Audience :: Developers
Classifier: License :: OSI Approved :: MIT License
Classifier: Operating System :: OS Independent
Classifier: Programming Language :: Python :: 3
Classifier: Programming Language :: Python :: 3.8
Classifier: Programming Language :: Python :: 3.9
Classifier: Programming Language :: Python :: 3.10
Classifier: Programming Language :: Python :: 3.11
Classifier: Programming Language :: Python :: 3.12
Classifier: Topic :: Software Development :: Libraries :: Python Modules
Classifier: Topic :: System :: Monitoring
Classifier: Topic :: Software Development :: Testing
Requires-Python: >=3.8
License-File: LICENSE
Requires-Dist: omegaconf>=2.3.0
Requires-Dist: psutil>=5.9.0
Requires-Dist: boto3>=1.26.0
Provides-Extra: dev
Requires-Dist: pytest>=7.0.0; extra == "dev"
Requires-Dist: pytest-cov>=4.0.0; extra == "dev"
Requires-Dist: black>=23.0.0; extra == "dev"
Requires-Dist: isort>=5.12.0; extra == "dev"
Requires-Dist: flake8>=6.0.0; extra == "dev"
Requires-Dist: mypy>=1.0.0; extra == "dev"
Requires-Dist: pre-commit>=3.0.0; extra == "dev"
Dynamic: license-file
